["{\"o\": [{\"start\": 0.9, \"stop\": 4.4, \"text\": \"Добрый день. Университет НТСИ. Меня зовут Ульяна. Как могу к вам обращаться?\"}, {\"start\": 17.4, \"stop\": 24.1, \"text\": \"Да, конечно, я могу Вам дать номер телефона иностранного деканата и, естественно, они Вас проконсультируют по поступлению иностранного гражданина.\"}, {\"start\": 27.3, \"stop\": 29.5, \"text\": \"\"}, {\"start\": 31.3, \"stop\": 32.9, \"text\": \"\"}, {\"start\": 34.8, \"stop\": 38.9, \"text\": \"86\"}, {\"start\": 41.2, \"stop\": 45.5, \"text\": \"и добавочные номера 190 и 193.\"}, {\"start\": 49.6, \"stop\": 52.4, \"text\": \"Пожалуйста. Всего доброго. До свидания.\"}], \"c\": [{\"start\": 4.9, \"stop\": 16.2, \"text\": \"Улиана, здравствуйте, меня зовут Евгений. Улиана, подскажите, пожалуйста, у меня такой вопрос. А к вам может поступить иностранец, а конкретно гражданин Узбекистана на обучение?\"}, {\"start\": 24.9, \"stop\": 26.2, \"text\": \"Да, я записываю.\"}, {\"start\": 33.7, \"stop\": 34.1, \"text\": \"Угу.\"}, {\"start\": 36.8, \"stop\": 37.2, \"text\": \"Угу.\"}, {\"start\": 39.9, \"stop\": 41.1, \"text\": \"\"}, {\"start\": 47.2, \"stop\": 50.2, \"text\": \"Всё хорошо. Большое спасибо, Ульяна. Записал. До свидания.\"}]}"]